LICENSE
README.md
setup.py
regex_inference/__init__.py
regex_inference/evaluator.py
regex_inference/utils.py
regex_inference/version.py
regex_inference.egg-info/PKG-INFO
regex_inference.egg-info/SOURCES.txt
regex_inference.egg-info/dependency_links.txt
regex_inference.egg-info/requires.txt
regex_inference.egg-info/top_level.txt
regex_inference/inference/__init__.py
regex_inference/inference/candidate.py
regex_inference/inference/chain.py
regex_inference/inference/engine.py
regex_inference/inference/fado.py
regex_inference/inference/filter.py
regex_inference/inference/main.py