Metadata-Version: 2.1
Name: regex-inference
Version: 0.2.2
Summary: Regex Inference Engine based on ChatGPT
Home-page: https://github.com/jeffrey82221/regex_inference
Author: jeffreylin
Author-email: jeffrey82221@gmail.com
License: UNKNOWN
Platform: UNKNOWN
Classifier: Programming Language :: Python :: 3
Classifier: License :: OSI Approved :: MIT License
Classifier: Operating System :: OS Independent
Requires-Python: >=3.8, !=3.11.*
License-File: LICENSE
